tea_chainquery/__init__.py
tea_chainquery/blockchain.py
tea_chainquery/cli.py
tests/__init__.py
tests/test_cli.py
tea_chainquery-0.1.2.dist-info/METADATA
tea_chainquery-0.1.2.dist-info/WHEEL
tea_chainquery-0.1.2.dist-info/entry_points.txt
tea_chainquery-0.1.2.dist-info/top_level.txt
tea_chainquery-0.1.2.dist-info/RECORD
