Metadata-Version: 2.4
Name: tea-chainquery
Version: 0.1.2
Summary: ChainQuery: A CLI tool for querying blockchain data
Home-page: https://github.com/idyweb/chainquery
Author: Idongesit Inyang
Author-email: inyangidongesit22@gmail.com
License: MIT
Project-URL: Source, https://github.com/idyweb/chainquery
Requires-Dist: web3>=5.0.0
Requires-Dist: click>=8.0.0
Requires-Dist: requests>=2.0.0
Dynamic: author
Dynamic: author-email
Dynamic: description
Dynamic: description-content-type
Dynamic: home-page
Dynamic: license
Dynamic: project-url
Dynamic: requires-dist
Dynamic: summary
